{
 "allow_comments": 0,
 "allow_delete": 0,
 "allow_edit": 0,
 "allow_incomplete": 0,
 "allow_multiple": 0,
 "allow_print": 0,
 "anonymous": 0,
 "apply_document_permissions": 0,
 "button_label": "Submit",
 "condition_json": "[]",
 "creation": "2024-05-06 22:42:37.400091",
 "doc_type": "FOSS Community Project",
 "docstatus": 0,
 "doctype": "Web Form",
 "idx": 0,
 "is_standard": 1,
 "list_columns": [],
 "login_required": 0,
 "max_attachment_size": 0,
 "modified": "2024-05-06 22:43:32.526155",
 "modified_by": "Administrator",
 "module": "FOSSUnited",
 "name": "submit-your-foss-project",
 "owner": "Administrator",
 "published": 1,
 "route": "submit-your-foss-project",
 "show_attachments": 0,
 "show_list": 0,
 "show_sidebar": 0,
 "title": "Submit your FOSS Project",
 "web_form_fields": [
  {
   "allow_read_on_all_link_options": 0,
   "fieldname": "details_section",
   "fieldtype": "Section Break",
   "hidden": 0,
   "label": "Details",
   "max_length": 0,
   "max_value": 0,
   "precision": "",
   "read_only": 0,
   "reqd": 0,
   "show_in_filter": 0
  },
  {
   "allow_read_on_all_link_options": 0,
   "fieldname": "project_name",
   "fieldtype": "Data",
   "hidden": 0,
   "label": "Project Name",
   "max_length": 0,
   "max_value": 0,
   "precision": "",
   "read_only": 0,
   "reqd": 1,
   "show_in_filter": 0
  },
  {
   "allow_read_on_all_link_options": 0,
   "fieldname": "url",
   "fieldtype": "Data",
   "hidden": 0,
   "label": "URL",
   "max_length": 0,
   "max_value": 0,
   "options": "URL",
   "precision": "",
   "read_only": 0,
   "reqd": 1,
   "show_in_filter": 0
  },
  {
   "allow_read_on_all_link_options": 0,
   "fieldname": "logo",
   "fieldtype": "Attach Image",
   "hidden": 0,
   "label": "Logo",
   "max_length": 0,
   "max_value": 0,
   "precision": "",
   "read_only": 0,
   "reqd": 0,
   "show_in_filter": 0
  },
  {
   "allow_read_on_all_link_options": 0,
   "fieldname": "headline",
   "fieldtype": "Small Text",
   "hidden": 0,
   "label": "Headline",
   "max_length": 0,
   "max_value": 0,
   "precision": "",
   "read_only": 0,
   "reqd": 0,
   "show_in_filter": 0
  },
  {
   "allow_read_on_all_link_options": 0,
   "fieldname": "organisation",
   "fieldtype": "Data",
   "hidden": 0,
   "label": "Organisation",
   "max_length": 0,
   "max_value": 0,
   "precision": "",
   "read_only": 0,
   "reqd": 0,
   "show_in_filter": 0
  },
  {
   "allow_read_on_all_link_options": 0,
   "fieldname": "section_break_kozf",
   "fieldtype": "Section Break",
   "hidden": 0,
   "label": "",
   "max_length": 0,
   "max_value": 0,
   "precision": "",
   "read_only": 0,
   "reqd": 0,
   "show_in_filter": 0
  },
  {
   "allow_read_on_all_link_options": 0,
   "default": "",
   "fieldname": "links",
   "fieldtype": "Table",
   "hidden": 0,
   "label": "Links",
   "max_length": 0,
   "max_value": 0,
   "options": "FOSS Community Project Links",
   "precision": "",
   "read_only": 0,
   "reqd": 0,
   "show_in_filter": 0
  },
  {
   "allow_read_on_all_link_options": 0,
   "fieldname": "section_break_cjwu",
   "fieldtype": "Section Break",
   "hidden": 0,
   "label": "",
   "max_length": 0,
   "max_value": 0,
   "precision": "",
   "read_only": 0,
   "reqd": 0,
   "show_in_filter": 0
  },
  {
   "allow_read_on_all_link_options": 0,
   "fieldname": "description",
   "fieldtype": "Text Editor",
   "hidden": 0,
   "label": "Description",
   "max_length": 0,
   "max_value": 0,
   "precision": "",
   "read_only": 0,
   "reqd": 0,
   "show_in_filter": 0
  }
 ]
}
